atlas_q/__init__.py
atlas_q/__main__.py
atlas_q/adaptive_mps.py
atlas_q/ansatz_uccsd.py
atlas_q/check_hamiltonian_coeffs.py
atlas_q/circuit_cutting.py
atlas_q/coherence_aware_vqe.py
atlas_q/cuquantum_backend.py
atlas_q/diagnostics.py
atlas_q/distributed_mps.py
atlas_q/grover.py
atlas_q/linalg_robust.py
atlas_q/mpo_ops.py
atlas_q/mps_pytorch.py
atlas_q/noise_models.py
atlas_q/peps.py
atlas_q/planar_2d.py
atlas_q/quantum_hybrid_system.py
atlas_q/sim_env_scan.py
atlas_q/sim_safety_checks.py
atlas_q/stabilizer_backend.py
atlas_q/tdvp.py
atlas_q/truncation.py
atlas_q/unitary_backends.py
atlas_q/vqe_qaoa.py
atlas_q/coherence/__init__.py
atlas_q/coherence/classification.py
atlas_q/coherence/metrics.py
atlas_q/coherence/utils.py
atlas_q/tools_qih/__init__.py
atlas_q/tools_qih/ai_rank_policy.py
atlas_q/tools_qih/ai_rank_predictor.py
atlas_q/tools_qih/chirp_features.py
atlas_q/tools_qih/finetuned_predictor.py
atlas_q/tools_qih/learned_period_head.py
atlas_q/tools_qih/ntt_features.py
atlas_q/tools_qih/periodic2d_features.py
atlas_q/tools_qih/periodic_mixture_features.py
atlas_q/tools_qih/qih_hf_collator.py
atlas_q/tools_qih/qih_llm.py
atlas_q/tools_qih/qih_pat.py
atlas_q/tools_qih/svd_logger.py
atlas_q/tools_qih/tn_core.py
atlas_q/tools_qih/tn_layers.py
atlas_q/vra_enhanced/__init__.py
atlas_q/vra_enhanced/core.py
atlas_q/vra_enhanced/gradient_grouping.py
atlas_q/vra_enhanced/qaoa_grouping.py
atlas_q/vra_enhanced/qpe_bridge.py
atlas_q/vra_enhanced/shadow_tomography.py
atlas_q/vra_enhanced/state_tomography.py
atlas_q/vra_enhanced/tdvp_observables.py
atlas_q/vra_enhanced/vqe_grouping.py
atlas_quantum-0.6.3.dist-info/licenses/LICENSE
triton_kernels/__init__.py
triton_kernels/modpow.py
triton_kernels/mps_complex.py
triton_kernels/mps_ops.py
triton_kernels/tdvp_mpo_ops.py
atlas_quantum-0.6.3.dist-info/METADATA
atlas_quantum-0.6.3.dist-info/WHEEL
atlas_quantum-0.6.3.dist-info/top_level.txt
atlas_quantum-0.6.3.dist-info/RECORD
