Metadata-Version: 2.4
Name: atlas-quantum
Version: 0.6.3
Summary: GPU-accelerated quantum tensor network simulator with coherence-aware VQE, adaptive MPS, molecular chemistry, VRA integration, and cuQuantum backend
Author: ATLAS-Q Development Team
Maintainer: ATLAS-Q Development Team
License: MIT
Project-URL: Homepage, https://github.com/followthesapper/ATLAS-Q
Project-URL: Documentation, https://github.com/followthesapper/ATLAS-Q/tree/main/docs
Project-URL: Repository, https://github.com/followthesapper/ATLAS-Q
Project-URL: Bug Tracker, https://github.com/followthesapper/ATLAS-Q/issues
Project-URL: Changelog, https://github.com/followthesapper/ATLAS-Q/blob/main/docs/CHANGELOG.md
Keywords: quantum,simulation,tensor-networks,mps,peps,vqe,coherence-aware,vra,qaoa,tdvp,period-finding,molecular-chemistry,circuit-cutting,gpu-acceleration,cuquantum,nisq
Classifier: Development Status :: 4 - Beta
Classifier: Intended Audience :: Science/Research
Classifier: Intended Audience :: Education
Classifier: Intended Audience :: Developers
Classifier: License :: OSI Approved :: MIT License
Classifier: Programming Language :: Python :: 3
Classifier: Programming Language :: Python :: 3.9
Classifier: Programming Language :: Python :: 3.10
Classifier: Programming Language :: Python :: 3.11
Classifier: Programming Language :: Python :: 3.12
Classifier: Topic :: Scientific/Engineering :: Physics
Classifier: Topic :: Scientific/Engineering :: Artificial Intelligence
Classifier: Topic :: Software Development :: Libraries :: Python Modules
Classifier: Operating System :: OS Independent
Requires-Python: >=3.9
License-File: LICENSE
Requires-Dist: numpy>=1.22
Requires-Dist: scipy>=1.10.0
Requires-Dist: matplotlib>=3.6
Requires-Dist: torch>=2.0.0
Provides-Extra: gpu
Requires-Dist: triton>=2.0.0; extra == "gpu"
Provides-Extra: cuquantum
Requires-Dist: cuquantum-python>=23.0.0; extra == "cuquantum"
Provides-Extra: chemistry
Requires-Dist: pyscf>=2.0.0; extra == "chemistry"
Requires-Dist: openfermion>=1.5.0; extra == "chemistry"
Requires-Dist: openfermionpyscf>=0.5.0; extra == "chemistry"
Provides-Extra: ml
Requires-Dist: scikit-learn>=1.0.0; extra == "ml"
Provides-Extra: dev
Requires-Dist: pytest>=7.3; extra == "dev"
Requires-Dist: pytest-cov>=4.0; extra == "dev"
Requires-Dist: black>=23.0; extra == "dev"
Requires-Dist: ruff>=0.0.260; extra == "dev"
Provides-Extra: notebooks
Requires-Dist: jupyter>=1.0; extra == "notebooks"
Requires-Dist: ipykernel>=6.22; extra == "notebooks"
Provides-Extra: all
Requires-Dist: atlas-quantum[chemistry,cuquantum,dev,gpu,ml,notebooks]; extra == "all"
Dynamic: license-file
